cuebiq_trino_mcp/__init__.py
cuebiq_trino_mcp/claude_desktop_config_example.json
cuebiq_trino_mcp/config.py
cuebiq_trino_mcp/server.py
cuebiq_trino_mcp/trino_client.py
cuebiq_trino_mcp/prompts/__init__.py
cuebiq_trino_mcp/resources/__init__.py
cuebiq_trino_mcp/tools/__init__.py
cuebiq_trino_mcp-0.0.4.dist-info/METADATA
cuebiq_trino_mcp-0.0.4.dist-info/WHEEL
cuebiq_trino_mcp-0.0.4.dist-info/entry_points.txt
cuebiq_trino_mcp-0.0.4.dist-info/RECORD
