Metadata-Version: 2.4
Name: cuebiq-trino-mcp
Version: 0.0.4
Summary: A MCP server project
Author-email: fbalicchia <fbalicchia@cuebiq.com>
Requires-Python: >=3.10
Requires-Dist: loguru>=0.7.3
Requires-Dist: mcp>=1.4.1
Requires-Dist: pydantic>=2.10.6
Requires-Dist: trino>=0.333.0
